pynewton/__init__.py
pynewton/boost_python310-vc143-mt-x64-1_79.dll
pynewton/newtonlib.pyd
pynewton/python310.dll
pynewton/zlib1.dll
newtonlib-0.0.4.dist-info/LICENSE.md
newtonlib-0.0.4.dist-info/METADATA
newtonlib-0.0.4.dist-info/WHEEL
newtonlib-0.0.4.dist-info/top_level.txt
newtonlib-0.0.4.dist-info/RECORD
