Metadata-Version: 2.1
Name: newtonlib
Version: 0.0.4
Summary: Python package for a university course
Home-page: https://git.e-science.pl/kwazny_252716_dpp/kwazny252716_pythonnative
Author: Karol Ważny
Author-email: kwazny_252716@e-science.pl
License: MIT
Platform: UNKNOWN
License-File: LICENSE.md
